src/AV3/AV3.py
src/AV3/__init__.py
dotsaddressvalidation3-1.0.3.dist-info/METADATA
dotsaddressvalidation3-1.0.3.dist-info/WHEEL
dotsaddressvalidation3-1.0.3.dist-info/licenses/LICENSE
dotsaddressvalidation3-1.0.3.dist-info/RECORD
