Metadata-Version: 2.1
Name: DOTSAddressValidation3
Version: 1.0.3
Summary: DOTS Address Validation 3 US (“AV3”) is a new version of our Address Validation and Address Validation 2 Web services. This service utilizes the latest version of python and can be used as a RESTful service. AV3 is designed to take an unstandardized address, validate it against the latest USPS data, and return standardized, deliverable addresses.
Project-URL: Homepage, https://www.serviceobjects.com/address-validation/
Author-email: "Service Objects, Inc." <support@serviceobjects.com>
License-File: LICENSE
Classifier: License :: OSI Approved :: MIT License
Classifier: Operating System :: OS Independent
Classifier: Programming Language :: Python :: 3
Requires-Python: >=3.7
